rethinkdbcm/__init__.py
rethinkdbcm/rethinkdbcm.py
rethinkdbcm-0.1.6.dist-info/LICENSE
rethinkdbcm-0.1.6.dist-info/METADATA
rethinkdbcm-0.1.6.dist-info/WHEEL
rethinkdbcm-0.1.6.dist-info/top_level.txt
rethinkdbcm-0.1.6.dist-info/RECORD
